odoo/addons/stock_release_channel_partner_delivery_window/README.rst
odoo/addons/stock_release_channel_partner_delivery_window/__init__.py
odoo/addons/stock_release_channel_partner_delivery_window/__manifest__.py
odoo/addons/stock_release_channel_partner_delivery_window/i18n/fr.po
odoo/addons/stock_release_channel_partner_delivery_window/i18n/it.po
odoo/addons/stock_release_channel_partner_delivery_window/i18n/stock_release_channel_partner_delivery_window.pot
odoo/addons/stock_release_channel_partner_delivery_window/models/__init__.py
odoo/addons/stock_release_channel_partner_delivery_window/models/stock_picking.py
odoo/addons/stock_release_channel_partner_delivery_window/models/stock_release_channel.py
odoo/addons/stock_release_channel_partner_delivery_window/readme/CONTRIBUTORS.md
odoo/addons/stock_release_channel_partner_delivery_window/readme/CREDITS.md
odoo/addons/stock_release_channel_partner_delivery_window/readme/DESCRIPTION.md
odoo/addons/stock_release_channel_partner_delivery_window/static/description/icon.png
odoo/addons/stock_release_channel_partner_delivery_window/static/description/index.html
odoo/addons/stock_release_channel_partner_delivery_window/tests/__init__.py
odoo/addons/stock_release_channel_partner_delivery_window/tests/test_release_window.py
odoo/addons/stock_release_channel_partner_delivery_window/views/stock_release_channel_view.xml
odoo_addon_stock_release_channel_partner_delivery_window-18.0.1.1.1.dist-info/METADATA
odoo_addon_stock_release_channel_partner_delivery_window-18.0.1.1.1.dist-info/WHEEL
odoo_addon_stock_release_channel_partner_delivery_window-18.0.1.1.1.dist-info/top_level.txt
odoo_addon_stock_release_channel_partner_delivery_window-18.0.1.1.1.dist-info/RECORD
