Metadata-Version: 2.1
Name: odoo-addon-stock_release_channel_partner_delivery_window
Version: 18.0.1.1.1
Requires-Python: >=3.10
Requires-Dist: odoo-addon-stock_partner_delivery_window==18.0.*
Requires-Dist: odoo-addon-stock_release_channel_shipment_lead_time==18.0.*
Requires-Dist: odoo==18.0.*
Summary: Allows to define an end date (and time) on a release channel and propagate it to the concerned pickings
Home-page: https://github.com/OCA/stock-logistics-release-channel
License: AGPL-3
Author: Camptocamp, BCIM, Odoo Community Association (OCA)
Author-email: support@odoo-community.org
Classifier: Programming Language :: Python
Classifier: Framework :: Odoo
Classifier: Framework :: Odoo :: 18.0
Classifier: License :: OSI Approved :: GNU Affero General Public License v3
